{
  "archivo": "amza65_1_260119175703281_MIT_01997.wav",
  "duracion_segundos": 598.02,
  "num_segmentos": 141,
  "num_hablantes": 2,
  "hablantes": [
    "Hablante A",
    "Hablante B"
  ],
  "tiempo_por_hablante": {
    "Hablante A": 324.44,
    "Hablante B": 233.2
  },
  "idioma": "es",
  "conversacion": [
    {
      "hablante": "Hablante A",
      "inicio": 0.12,
      "fin": 12.33,
      "duracion": 12.21,
      "texto": "Hola, buenas tardes.",
      "confianza": 0.45,
      "texto_original": "Hola, buenas tardes.",
      "rol": "AGENTE"
    },
    {
      "hablante": "Hablante A",
      "inicio": 12.95,
      "fin": 24.02,
      "duracion": 11.07,
      "texto": "Hola, es Javier, un gusto.",
      "confianza": 0.377,
      "texto_original": "Hola, es Javier, un gusto.",
      "rol": "AGENTE"
    },
    {
      "hablante": "Hablante A",
      "inicio": 24.04,
      "fin": 30.12,
      "duracion": 6.09,
      "texto": "Les estoy hablando desde la área de portabilidad de Modestar.",
      "confianza": 0.518,
      "texto_original": "Les estoy hablando desde la área de portabilidad de Modestar.",
      "rol": "AGENTE"
    },
    {
      "hablante": "Hablante A",
      "inicio": 30.29,
      "fin": 38.6,
      "duracion": 8.31,
      "texto": "Muy bien, era para comentarles las promociones, se han actualizado y tenemos algo con mayor cantidad de gigas y un poco más económico.",
      "confianza": 0.738,
      "texto_original": "Muy bien, era para comentarles las promociones, se han actualizado y tenemos algo con mayor cantidad de gigas y un poco más económico.",
      "rol": "AGENTE"
    },
    {
      "hablante": "Hablante B",
      "inicio": 41.52,
      "fin": 42.98,
      "duracion": 1.46,
      "texto": "Le comento las promociones.",
      "confianza": 0.491,
      "texto_original": "Le comento las promociones.",
      "rol": "CLIENTE"
    },
    {
      "hablante": "Hablante B",
      "inicio": 43.15,
      "fin": 53.36,
      "duracion": 10.21,
      "texto": "Tenemos lo que sería un plan de 14 gigass en $6,450 pesos y otro plan de 18 gigass en $8,000 pesos.",
      "confianza": 0.659,
      "texto_original": "Tenemos lo que sería un plan de 14 gigas en $6,450 pesos y otro plan de 18 gigas en $8,000 pesos.",
      "rol": "CLIENTE"
    },
    {
      "hablante": "Hablante B",
      "inicio": 53.86,
      "fin": 58.77,
      "duracion": 4.91,
      "texto": "El más económico me interesa.",
      "confianza": 0.378,
      "texto_original": "El más económico me interesa.",
      "rol": "CLIENTE"
    },
    {
      "hablante": "Hablante B",
      "inicio": 58.79,
      "fin": 59.53,
      "duracion": 0.74,
      "texto": "El de $6.450?",
      "confianza": 0.546,
      "texto_original": "El de $6.450?",
      "rol": "CLIENTE"
    },
    {
      "hablante": "Hablante B",
      "inicio": 59.59,
      "fin": 59.71,
      "duracion": 0.12,
      "texto": "Sí.",
      "confianza": 0.585,
      "texto_original": "Sí.",
      "rol": "CLIENTE"
    },
    {
      "hablante": "Hablante B",
      "inicio": 59.73,
      "fin": 63.13,
      "duracion": 3.4,
      "texto": "¿Precio pico?",
      "confianza": 0.474,
      "texto_original": "¿Precio pico?",
      "rol": "CLIENTE"
    },
    {
      "hablante": "Hablante B",
      "inicio": 63.16,
      "fin": 63.44,
      "duracion": 0.28,
      "texto": "¿Cómo?",
      "confianza": 0.576,
      "texto_original": "¿Cómo?",
      "rol": "CLIENTE"
    },
    {
      "hablante": "Hablante A",
      "inicio": 65.12,
      "fin": 66.98,
      "duracion": 1.86,
      "texto": "¿Este monte es pico?",
      "confianza": 0.267,
      "texto_original": "¿Este monte es pico?",
      "rol": "AGENTE"
    },
    {
      "hablante": "Hablante A",
      "inicio": 67.0,
      "fin": 67.72,
      "duracion": 0.72,
      "texto": "Sí, totalmente.",
      "confianza": 0.682,
      "texto_original": "Sí, totalmente.",
      "rol": "AGENTE"
    },
    {
      "hablante": "Hablante A",
      "inicio": 68.36,
      "fin": 76.59,
      "duracion": 8.23,
      "texto": "Tiene un descuento... Yo me cambié de línea porque la verdad es que la verdad es que me agundaron 10.000 veces a movistar.",
      "confianza": 0.399,
      "texto_original": "Tiene un descuento... Yo me cambié de línea porque la verdad es que la verdad es que me agundaron 10.000 veces a movistar.",
      "rol": "AGENTE"
    },
    {
      "hablante": "Hablante A",
      "inicio": 76.61,
      "fin": 78.17,
      "duracion": 1.56,
      "texto": "Por eso me cambié a claro.",
      "confianza": 0.4,
      "texto_original": "Por eso me cambié a claro.",
      "rol": "AGENTE"
    },
    {
      "hablante": "Hablante A",
      "inicio": 78.19,
      "fin": 78.96,
      "duracion": 0.76,
      "texto": "Claro, sí, sí, sí.",
      "confianza": 0.245,
      "texto_original": "Claro, sí, sí, sí.",
      "rol": "AGENTE"
    },
    {
      "hablante": "Hablante A",
      "inicio": 79.16,
      "fin": 80.24,
      "duracion": 1.08,
      "texto": "La entiendo totalmente.",
      "confianza": 0.798,
      "texto_original": "La entiendo totalmente.",
      "rol": "AGENTE"
    },
    {
      "hablante": "Hablante A",
      "inicio": 80.26,
      "fin": 83.58,
      "duracion": 3.32,
      "texto": "Sí, ese precio pico es un descuento durante $6.000.",
      "confianza": 0.66,
      "texto_original": "Sí, ese precio pico es un descuento durante $6.000.",
      "rol": "AGENTE"
    },
    {
      "hablante": "Hablante A",
      "inicio": 83.83,
      "fin": 94.63,
      "duracion": 10.8,
      "texto": "Yo siempre les digo a mis clientes que en el quinto mes lo pueden, digamos, actualizar al plan para evitar que le venga el valor total del plan antes de que se le venga la promoción.",
      "confianza": 0.748,
      "texto_original": "Yo siempre les digo a mis clientes que en el quinto mes lo pueden, digamos, actualizar al plan para evitar que le venga el valor total del plan antes de que se le venga la promoción.",
      "rol": "AGENTE"
    },
    {
      "hablante": "Hablante A",
      "inicio": 94.65,
      "fin": 96.79,
      "duracion": 2.14,
      "texto": "¿Entiendes?",
      "confianza": 0.329,
      "texto_original": "¿Entiendes?",
      "rol": "AGENTE"
    },
    {
      "hablante": "Hablante A",
      "inicio": 96.81,
      "fin": 104.99,
      "duracion": 8.17,
      "texto": "Y bueno, lo actualizo ustedes en la aplicación de Movistar y sigue gozando de los mismos beneficios.",
      "confianza": 0.625,
      "texto_original": "Y bueno, lo actualizo ustedes en la aplicación de Movistar y sigue gozando de los mismos beneficios.",
      "rol": "AGENTE"
    },
    {
      "hablante": "Hablante A",
      "inicio": 105.01,
      "fin": 105.69,
      "duracion": 0.68,
      "texto": "¿Cómo?",
      "confianza": 0.689,
      "texto_original": "¿Cómo?",
      "rol": "AGENTE"
    },
    {
      "hablante": "Hablante A",
      "inicio": 106.06,
      "fin": 109.28,
      "duracion": 3.22,
      "texto": "¿Te lo conservo?",
      "confianza": 0.414,
      "texto_original": "¿Te lo conservo?",
      "rol": "AGENTE"
    },
    {
      "hablante": "Hablante A",
      "inicio": 109.3,
      "fin": 113.71,
      "duracion": 4.41,
      "texto": "Sí, va a seguir teniendo el mismo número, solamente que se va a cambiar de compañía.",
      "confianza": 0.703,
      "texto_original": "Sí, va a seguir teniendo el mismo número, solamente que se va a cambiar de compañía.",
      "rol": "AGENTE"
    },
    {
      "hablante": "Hablante A",
      "inicio": 113.73,
      "fin": 124.66,
      "duracion": 10.94,
      "texto": "Y bueno, le comento que usted también tiene WhatsApp gratis, llamadas libres a cualquier compañía y 20 días de regalo durante 30 días, que usted los activa en el momento en el que lo desea usar.",
      "confianza": 0.563,
      "texto_original": "Y bueno, le comento que usted también tiene WhatsApp gratis, llamadas libres a cualquier compañía y 20 días de regalo durante 30 días, que usted los activa en el momento en el que lo desea usar.",
      "rol": "AGENTE"
    },
    {
      "hablante": "Hablante A",
      "inicio": 124.68,
      "fin": 126.27,
      "duracion": 1.58,
      "texto": "¿Seguimos entonces con panista la promoción?",
      "confianza": 0.412,
      "texto_original": "¿Seguimos entonces con panista la promoción?",
      "rol": "AGENTE"
    },
    {
      "hablante": "Hablante B",
      "inicio": 127.85,
      "fin": 131.69,
      "duracion": 3.85,
      "texto": "Sí, pero mira, yo quiero que sea tipo, que normativa que sea poeta.",
      "confianza": 0.421,
      "texto_original": "Sí, pero mira, yo quiero que sea tipo, que normativa que sea poeta.",
      "rol": "CLIENTE"
    },
    {
      "hablante": "Hablante B",
      "inicio": 131.89,
      "fin": 139.6,
      "duracion": 7.71,
      "texto": "Hace dos meses me meten el abono.",
      "confianza": 0.598,
      "texto_original": "Hace dos meses me meten el abono.",
      "rol": "CLIENTE"
    },
    {
      "hablante": "Hablante B",
      "inicio": 139.62,
      "fin": 141.19,
      "duracion": 1.56,
      "texto": "Sí, lo entiendo totalmente.",
      "confianza": 0.67,
      "texto_original": "Sí, lo entiendo totalmente.",
      "rol": "CLIENTE"
    },
    {
      "hablante": "Hablante B",
      "inicio": 141.61,
      "fin": 153.34,
      "duracion": 11.74,
      "texto": "Duran seis meses la promoción, se mantiene el precio y después cualquier cosa que usted lo tiene que cambiar a la promoción o supongas que necesita más vidas o algo así lo puede excepcionar en la aplicación.",
      "confianza": 0.632,
      "texto_original": "Duran seis meses la promoción, se mantiene el precio y después cualquier cosa que usted lo tiene que cambiar a la promoción o supongas que necesita más vidas o algo así lo puede excepcionar en la aplicación.",
      "rol": "CLIENTE"
    },
    {
      "hablante": "Hablante B",
      "inicio": 153.93,
      "fin": 154.63,
      "duracion": 0.7,
      "texto": "Sí, a mí se me pasó.",
      "confianza": 0.353,
      "texto_original": "Sí, a mí se me pasó.",
      "rol": "CLIENTE"
    },
    {
      "hablante": "Hablante B",
      "inicio": 154.91,
      "fin": 158.34,
      "duracion": 3.43,
      "texto": "y buscar alguna cosa y poder hacer otra cosa.",
      "confianza": 0.446,
      "texto_original": "y buscar alguna cosa y poder hacer otra cosa.",
      "rol": "CLIENTE"
    },
    {
      "hablante": "Hablante B",
      "inicio": 158.35,
      "fin": 161.06,
      "duracion": 2.7,
      "texto": "Claro, sí sí.",
      "confianza": 0.258,
      "texto_original": "Claro, sí sí.",
      "rol": "CLIENTE"
    },
    {
      "hablante": "Hablante B",
      "inicio": 161.08,
      "fin": 163.48,
      "duracion": 2.4,
      "texto": "Pero bueno, si...",
      "confianza": 0.7,
      "texto_original": "Pero bueno, si...",
      "rol": "CLIENTE"
    },
    {
      "hablante": "Hablante B",
      "inicio": 163.5,
      "fin": 164.42,
      "duracion": 0.92,
      "texto": "Lo hacemos.",
      "confianza": 0.585,
      "texto_original": "Lo hacemos.",
      "rol": "CLIENTE"
    },
    {
      "hablante": "Hablante B",
      "inicio": 164.52,
      "fin": 171.41,
      "duracion": 6.89,
      "texto": "Bueno, entonces, ¿necesitaría que me pase un correo electrónico que a ese le van a llegar las facturas?",
      "confianza": 0.661,
      "texto_original": "Bueno, entonces, ¿necesitaría que me pase un correo electrónico que a ese le van a llegar las facturas?",
      "rol": "CLIENTE"
    },
    {
      "hablante": "Hablante B",
      "inicio": 171.43,
      "fin": 174.12,
      "duracion": 2.68,
      "texto": "Sí.",
      "confianza": 0.619,
      "texto_original": "Sí.",
      "rol": "CLIENTE"
    },
    {
      "hablante": "Hablante B",
      "inicio": 174.14,
      "fin": 176.16,
      "duracion": 2.02,
      "texto": "Dígame.",
      "confianza": 0.749,
      "texto_original": "Dígame.",
      "rol": "CLIENTE"
    },
    {
      "hablante": "Hablante B",
      "inicio": 176.18,
      "fin": 181.95,
      "duracion": 5.77,
      "texto": "No, pero es que... Más que que levantar, yo con eso... Quiero... No, yo no creo que venga nunca.",
      "confianza": 0.536,
      "texto_original": "No, pero es que... Más que que levantar, yo con eso... Quiero... No, yo no creo que venga nunca.",
      "rol": "CLIENTE"
    },
    {
      "hablante": "Hablante B",
      "inicio": 182.5,
      "fin": 185.94,
      "duracion": 3.44,
      "texto": "¿Puede ser mañana?",
      "confianza": 0.275,
      "texto_original": "¿Puede ser mañana?",
      "rol": "CLIENTE"
    },
    {
      "hablante": "Hablante B",
      "inicio": 185.97,
      "fin": 186.81,
      "duracion": 0.84,
      "texto": "No, no hay problema.",
      "confianza": 0.74,
      "texto_original": "No, no hay problema.",
      "rol": "CLIENTE"
    },
    {
      "hablante": "Hablante B",
      "inicio": 186.87,
      "fin": 190.21,
      "duracion": 3.34,
      "texto": "Al final, después de última, me lo paso a usted mañana y yo lo adjunto.",
      "confianza": 0.607,
      "texto_original": "Al final, después de última, me lo paso a usted mañana y yo lo adjunto.",
      "rol": "CLIENTE"
    },
    {
      "hablante": "Hablante B",
      "inicio": 191.49,
      "fin": 193.98,
      "duracion": 2.48,
      "texto": "O si no me fijo, ¿cuál me asegura con el sistema?",
      "confianza": 0.662,
      "texto_original": "O si no me fijo, ¿cuál me asegura con el sistema?",
      "rol": "CLIENTE"
    },
    {
      "hablante": "Hablante B",
      "inicio": 194.02,
      "fin": 197.04,
      "duracion": 3.03,
      "texto": "Le pregunto a ver si usted más o menos se acuerda, si es el de firme.",
      "confianza": 0.537,
      "texto_original": "Le pregunto a ver si usted más o menos se acuerda, si es el de firme.",
      "rol": "CLIENTE"
    },
    {
      "hablante": "Hablante B",
      "inicio": 197.06,
      "fin": 201.55,
      "duracion": 4.49,
      "texto": "Y si no, cualquier cosita lo asuntamos mañana.",
      "confianza": 0.802,
      "texto_original": "Y si no, cualquier cosita lo asuntamos mañana.",
      "rol": "CLIENTE"
    },
    {
      "hablante": "Hablante B",
      "inicio": 201.79,
      "fin": 203.99,
      "duracion": 2.2,
      "texto": "No hay ningún tipo de problema.",
      "confianza": 0.416,
      "texto_original": "No hay ningún tipo de problema.",
      "rol": "CLIENTE"
    },
    {
      "hablante": "Hablante B",
      "inicio": 204.01,
      "fin": 209.04,
      "duracion": 5.03,
      "texto": "Yo en eso estoy totalmente analógico.",
      "confianza": 0.56,
      "texto_original": "Yo en eso estoy totalmente analógico.",
      "rol": "CLIENTE"
    },
    {
      "hablante": "Hablante B",
      "inicio": 209.06,
      "fin": 210.04,
      "duracion": 0.98,
      "texto": "No hay problema.",
      "confianza": 0.713,
      "texto_original": "No hay problema.",
      "rol": "CLIENTE"
    },
    {
      "hablante": "Hablante B",
      "inicio": 210.8,
      "fin": 211.34,
      "duracion": 0.54,
      "texto": "Lo entiendo.",
      "confianza": 0.514,
      "texto_original": "Lo entiendo.",
      "rol": "CLIENTE"
    },
    {
      "hablante": "Hablante B",
      "inicio": 211.56,
      "fin": 226.72,
      "duracion": 15.16,
      "texto": "Bueno, bueno, bien.",
      "confianza": 0.444,
      "texto_original": "Bueno, bueno, bien.",
      "rol": "CLIENTE"
    },
    {
      "hablante": "Hablante B",
      "inicio": 227.13,
      "fin": 257.14,
      "duracion": 30.01,
      "texto": "¿Tiene únicamente este número de teléfono o algún otro a su nombre?",
      "confianza": 0.712,
      "texto_original": "¿Tiene únicamente este número de teléfono o algún otro a su nombre?",
      "rol": "CLIENTE"
    },
    {
      "hablante": "Hablante B",
      "inicio": 257.69,
      "fin": 263.02,
      "duracion": 5.33,
      "texto": "Bueno, a ver, aguardemos un segundito, le hago una consulta.",
      "confianza": 0.536,
      "texto_original": "Bueno, a ver, aguardemos un segundito, le hago una consulta.",
      "rol": "CLIENTE"
    },
    {
      "hablante": "Hablante B",
      "inicio": 263.04,
      "fin": 266.95,
      "duracion": 3.91,
      "texto": "¿Usted tiene chip físico, lo que es la tarjetita de grabada que se pone en el dispositivo?",
      "confianza": 0.689,
      "texto_original": "¿Usted tiene chip físico, lo que es la tarjetita de grabada que se pone en el dispositivo?",
      "rol": "CLIENTE"
    },
    {
      "hablante": "Hablante B",
      "inicio": 266.97,
      "fin": 273.96,
      "duracion": 6.99,
      "texto": "¿Usted tiene chip físico, que es la tarjetita de grabada que se pone en el celular?",
      "confianza": 0.671,
      "texto_original": "¿Usted tiene chip físico, que es la tarjetita de grabada que se pone en el celular?",
      "rol": "CLIENTE"
    },
    {
      "hablante": "Hablante A",
      "inicio": 276.04,
      "fin": 282.39,
      "duracion": 6.35,
      "texto": "Bien, me podría decir entonces, su provincia de localidad sigue haciendo una supersal para que vaya a retirar su morado chip de Movistar.",
      "confianza": 0.702,
      "texto_original": "Bien, me podría decir entonces, su provincia de localidad sigue haciendo una supersal para que vaya a retirar su morado chip de Movistar.",
      "rol": "AGENTE"
    },
    {
      "hablante": "Hablante A",
      "inicio": 283.19,
      "fin": 289.08,
      "duracion": 5.89,
      "texto": "Yo voy a estar en Pilar, por ahí está bueno el aire.",
      "confianza": 0.149,
      "texto_original": "Yo voy a estar en Pilar, por ahí está bueno el aire.",
      "rol": "AGENTE"
    },
    {
      "hablante": "Hablante A",
      "inicio": 289.1,
      "fin": 289.34,
      "duracion": 0.24,
      "texto": "Bien, a ver.",
      "confianza": 0.06,
      "texto_original": "Bien, a ver.",
      "rol": "AGENTE"
    },
    {
      "hablante": "Hablante A",
      "inicio": 289.36,
      "fin": 292.13,
      "duracion": 2.76,
      "texto": "A guardar un segundito que ahí le digo cuál me figura.",
      "confianza": 0.36,
      "texto_original": "A guardar un segundito que ahí le digo cuál me figura.",
      "rol": "AGENTE"
    },
    {
      "hablante": "Hablante A",
      "inicio": 292.15,
      "fin": 298.82,
      "duracion": 6.67,
      "texto": "Me figura una por la calle Río Dabia.",
      "confianza": 0.671,
      "texto_original": "Me figura una por la calle Río Dabia.",
      "rol": "AGENTE"
    },
    {
      "hablante": "Hablante A",
      "inicio": 298.84,
      "fin": 299.54,
      "duracion": 0.7,
      "texto": "Hablaste por San.",
      "confianza": 0.465,
      "texto_original": "Hablaste por San.",
      "rol": "AGENTE"
    },
    {
      "hablante": "Hablante A",
      "inicio": 300.24,
      "fin": 306.13,
      "duracion": 5.89,
      "texto": "Exactamente, por la calle Río Dabia y otra por la calle Tupumán en Chile.",
      "confianza": 0.709,
      "texto_original": "Exactamente, por la calle Río Dabia y otra por la calle Tupumán en Chile.",
      "rol": "AGENTE"
    },
    {
      "hablante": "Hablante A",
      "inicio": 306.15,
      "fin": 306.39,
      "duracion": 0.24,
      "texto": "Sí, conozco.",
      "confianza": 0.039,
      "texto_original": "Sí, conozco.",
      "rol": "AGENTE"
    },
    {
      "hablante": "Hablante A",
      "inicio": 306.41,
      "fin": 312.04,
      "duracion": 5.63,
      "texto": "Bien, le voy a signar la de la calle Río Dabia que tiene mayor cantidad de horario de atención.",
      "confianza": 0.663,
      "texto_original": "Bien, le voy a signar la de la calle Río Dabia que tiene mayor cantidad de horario de atención.",
      "rol": "AGENTE"
    },
    {
      "hablante": "Hablante A",
      "inicio": 312.25,
      "fin": 312.49,
      "duracion": 0.24,
      "texto": "Sí.",
      "confianza": 0.351,
      "texto_original": "Sí.",
      "rol": "AGENTE"
    },
    {
      "hablante": "Hablante A",
      "inicio": 312.51,
      "fin": 314.21,
      "duracion": 1.7,
      "texto": "Sí, que vale, dale.",
      "confianza": 0.358,
      "texto_original": "Sí, que vale, dale.",
      "rol": "AGENTE"
    },
    {
      "hablante": "Hablante A",
      "inicio": 314.6,
      "fin": 315.34,
      "duracion": 0.74,
      "texto": "Te lo voy a mandar.",
      "confianza": 0.537,
      "texto_original": "Te lo voy a mandar.",
      "rol": "AGENTE"
    },
    {
      "hablante": "Hablante A",
      "inicio": 315.36,
      "fin": 316.24,
      "duracion": 0.88,
      "texto": "¿Te lo mando a la domicilio?",
      "confianza": 0.144,
      "texto_original": "¿Te lo mando a la domicilio?",
      "rol": "AGENTE"
    },
    {
      "hablante": "Hablante A",
      "inicio": 316.26,
      "fin": 318.76,
      "duracion": 2.5,
      "texto": "¿Cómo?",
      "confianza": 0.825,
      "texto_original": "¿Cómo?",
      "rol": "AGENTE"
    },
    {
      "hablante": "Hablante A",
      "inicio": 318.78,
      "fin": 320.2,
      "duracion": 1.42,
      "texto": "¿Te lo mando a la domicilio eso?",
      "confianza": 0.408,
      "texto_original": "¿Te lo mando a la domicilio eso?",
      "rol": "AGENTE"
    },
    {
      "hablante": "Hablante A",
      "inicio": 321.02,
      "fin": 321.61,
      "duracion": 0.58,
      "texto": "Eh, no, no, no.",
      "confianza": 0.33,
      "texto_original": "Eh, no, no, no.",
      "rol": "AGENTE"
    },
    {
      "hablante": "Hablante A",
      "inicio": 321.63,
      "fin": 325.55,
      "duracion": 3.93,
      "texto": "Usted tiene que ir a retirar su chip a esa sucursal.",
      "confianza": 0.703,
      "texto_original": "Usted tiene que ir a retirar su chip a esa sucursal.",
      "rol": "AGENTE"
    },
    {
      "hablante": "Hablante A",
      "inicio": 325.57,
      "fin": 326.11,
      "duracion": 0.54,
      "texto": "Listo, bueno.",
      "confianza": 0.604,
      "texto_original": "Listo, bueno.",
      "rol": "AGENTE"
    },
    {
      "hablante": "Hablante A",
      "inicio": 326.13,
      "fin": 329.06,
      "duracion": 2.92,
      "texto": "Vos avisadme cuando tengo que ir a buscarlo y yo voy luego.",
      "confianza": 0.439,
      "texto_original": "Vos avisadme cuando tengo que ir a buscarlo y yo voy luego.",
      "rol": "AGENTE"
    },
    {
      "hablante": "Hablante A",
      "inicio": 329.08,
      "fin": 330.9,
      "duracion": 1.82,
      "texto": "Sí, ya mañana mismo lo puede ir a buscar.",
      "confianza": 0.643,
      "texto_original": "Sí, ya mañana mismo lo puede ir a buscar.",
      "rol": "AGENTE"
    },
    {
      "hablante": "Hablante A",
      "inicio": 330.92,
      "fin": 337.41,
      "duracion": 6.49,
      "texto": "Ahí le acabo de mandarlo horarios de atención por WhatsApp y ¿dónde está ubicada la sucursal?",
      "confianza": 0.518,
      "texto_original": "Ahí le acabo de mandarlo horarios de atención por WhatsApp y ¿dónde está ubicada la sucursal?",
      "rol": "AGENTE"
    },
    {
      "hablante": "Hablante A",
      "inicio": 337.43,
      "fin": 339.23,
      "duracion": 1.8,
      "texto": "Sí, lo conozco, en la esquina, lo conozco.",
      "confianza": 0.208,
      "texto_original": "Sí, lo conozco, en la esquina, lo conozco.",
      "rol": "AGENTE"
    },
    {
      "hablante": "Hablante A",
      "inicio": 339.25,
      "fin": 339.97,
      "duracion": 0.72,
      "texto": "Bien, perfecto.",
      "confianza": 0.329,
      "texto_original": "Bien, perfecto.",
      "rol": "AGENTE"
    },
    {
      "hablante": "Hablante A",
      "inicio": 340.67,
      "fin": 341.95,
      "duracion": 1.28,
      "texto": "Eh, a ver.",
      "confianza": 0.682,
      "texto_original": "Eh, a ver.",
      "rol": "AGENTE"
    },
    {
      "hablante": "Hablante A",
      "inicio": 342.75,
      "fin": 349.11,
      "duracion": 6.37,
      "texto": "No voy a fijar... No, no me figura ningún correo electrónico en el sistema, así que apenas puede charlar con tu hija, me avisa.",
      "confianza": 0.468,
      "texto_original": "No voy a fijar... No, no me figura ningún correo electrónico en el sistema, así que apenas puede charlar con tu hija, me avisa.",
      "rol": "AGENTE"
    },
    {
      "hablante": "Hablante A",
      "inicio": 349.67,
      "fin": 352.06,
      "duracion": 2.38,
      "texto": "Dale, dale, dale, se te avisa.",
      "confianza": 0.507,
      "texto_original": "Dale, dale, dale, se te avisa.",
      "rol": "AGENTE"
    },
    {
      "hablante": "Hablante A",
      "inicio": 352.08,
      "fin": 356.18,
      "duracion": 4.11,
      "texto": "A ver, el tema es que escute conmigo mi nieta, ¿viste?",
      "confianza": 0.488,
      "texto_original": "A ver, el tema es que escute conmigo mi nieta, ¿viste?",
      "rol": "AGENTE"
    },
    {
      "hablante": "Hablante A",
      "inicio": 356.2,
      "fin": 356.28,
      "duracion": 0.08,
      "texto": "Hoy.",
      "confianza": 0.146,
      "texto_original": "Hoy.",
      "rol": "AGENTE"
    },
    {
      "hablante": "Hablante A",
      "inicio": 356.3,
      "fin": 359.67,
      "duracion": 3.36,
      "texto": "Y yo me voy a la casa a trabajar y nunca viene más tarde.",
      "confianza": 0.292,
      "texto_original": "Y yo me voy a la casa a trabajar y nunca viene más tarde.",
      "rol": "AGENTE"
    },
    {
      "hablante": "Hablante A",
      "inicio": 359.69,
      "fin": 365.17,
      "duracion": 5.49,
      "texto": "Así le pregunto si lo puedo pasar hoy, si no, mañana a mi mamá si lo puedo pasar.",
      "confianza": 0.483,
      "texto_original": "Así le pregunto si lo puedo pasar hoy, si no, mañana a mi mamá si lo puedo pasar.",
      "rol": "AGENTE"
    },
    {
      "hablante": "Hablante A",
      "inicio": 365.19,
      "fin": 365.87,
      "duracion": 0.68,
      "texto": "Bueno, no es problema.",
      "confianza": 0.298,
      "texto_original": "Bueno, no es problema.",
      "rol": "AGENTE"
    },
    {
      "hablante": "Hablante A",
      "inicio": 366.27,
      "fin": 367.36,
      "duracion": 1.08,
      "texto": "Genial.",
      "confianza": 0.663,
      "texto_original": "Genial.",
      "rol": "AGENTE"
    },
    {
      "hablante": "Hablante A",
      "inicio": 367.38,
      "fin": 367.98,
      "duracion": 0.6,
      "texto": "Si eres hoy, mejor.",
      "confianza": 0.346,
      "texto_original": "Si eres hoy, mejor.",
      "rol": "AGENTE"
    },
    {
      "hablante": "Hablante A",
      "inicio": 368.42,
      "fin": 370.44,
      "duracion": 2.02,
      "texto": "Bien, entonces...",
      "confianza": 0.728,
      "texto_original": "Bien, entonces...",
      "rol": "AGENTE"
    },
    {
      "hablante": "Hablante A",
      "inicio": 370.82,
      "fin": 377.89,
      "duracion": 7.07,
      "texto": "Sí, sí, sí, eso tranquilo.",
      "confianza": 0.086,
      "texto_original": "Sí, sí, sí, eso tranquilo.",
      "rol": "AGENTE"
    },
    {
      "hablante": "Hablante A",
      "inicio": 377.91,
      "fin": 380.96,
      "duracion": 3.04,
      "texto": "Voy, voy, te mando un roll que te hiciera un misil, eh.",
      "confianza": 0.167,
      "texto_original": "Voy, voy, te mando un roll que te hiciera un misil, eh.",
      "rol": "AGENTE"
    },
    {
      "hablante": "Hablante A",
      "inicio": 380.98,
      "fin": 381.48,
      "duracion": 0.5,
      "texto": "No, bueno, un montón, eh.",
      "confianza": 0.03,
      "texto_original": "No, bueno, un montón, eh.",
      "rol": "AGENTE"
    },
    {
      "hablante": "Hablante A",
      "inicio": 381.5,
      "fin": 381.88,
      "duracion": 0.38,
      "texto": "Un poco para tanto.",
      "confianza": 0.022,
      "texto_original": "Un poco para tanto.",
      "rol": "AGENTE"
    },
    {
      "hablante": "Hablante A",
      "inicio": 381.9,
      "fin": 382.24,
      "duracion": 0.34,
      "texto": "Vale, vale, vale.",
      "confianza": 0.03,
      "texto_original": "Vale, vale, vale.",
      "rol": "AGENTE"
    },
    {
      "hablante": "Hablante A",
      "inicio": 382.26,
      "fin": 385.88,
      "duracion": 3.62,
      "texto": "Bueno, entonces, oye, ahora le voy a empezar a hacer un cierre comercial, ¿sí?",
      "confianza": 0.595,
      "texto_original": "Bueno, entonces, oye, ahora le voy a empezar a hacer un cierre comercial, ¿sí?",
      "rol": "AGENTE"
    },
    {
      "hablante": "Hablante A",
      "inicio": 386.48,
      "fin": 396.07,
      "duracion": 9.59,
      "texto": "Esto es para corroborar de que todos los datos, eh, que ustedes estén bien, que hayan entendido cómo se realiza todo el proceso, si tienen alguna movilidad, primer frena, y lo corroboramos.",
      "confianza": 0.717,
      "texto_original": "Esto es para corroborar de que todos los datos, eh, que ustedes estén bien, que hayan entendido cómo se realiza todo el proceso, si tienen alguna movilidad, primer frena, y lo corroboramos.",
      "rol": "AGENTE"
    },
    {
      "hablante": "Hablante A",
      "inicio": 396.63,
      "fin": 399.93,
      "duracion": 3.31,
      "texto": "Pero no, antes le voy a mandar el código de portabilidad.",
      "confianza": 0.674,
      "texto_original": "Pero no, antes le voy a mandar el código de portabilidad.",
      "rol": "AGENTE"
    },
    {
      "hablante": "Hablante A",
      "inicio": 399.95,
      "fin": 402.18,
      "duracion": 2.22,
      "texto": "¿Sabe cómo ver los mensajes del texto, verdad?",
      "confianza": 0.686,
      "texto_original": "¿Sabe cómo ver los mensajes del texto, verdad?",
      "rol": "AGENTE"
    },
    {
      "hablante": "Hablante A",
      "inicio": 403.6,
      "fin": 404.32,
      "duracion": 0.72,
      "texto": "Sí, sí.",
      "confianza": 0.341,
      "texto_original": "Sí, sí.",
      "rol": "AGENTE"
    },
    {
      "hablante": "Hablante A",
      "inicio": 404.34,
      "fin": 405.1,
      "duracion": 0.76,
      "texto": "Bien, perfecto.",
      "confianza": 0.288,
      "texto_original": "Bien, perfecto.",
      "rol": "AGENTE"
    },
    {
      "hablante": "Hablante A",
      "inicio": 405.12,
      "fin": 408.38,
      "duracion": 3.26,
      "texto": "Entonces, yo ya, cuando le llegue, le aviso.",
      "confianza": 0.673,
      "texto_original": "Entonces, yo ya, cuando le llegue, le aviso.",
      "rol": "AGENTE"
    },
    {
      "hablante": "Hablante A",
      "inicio": 409.43,
      "fin": 416.26,
      "duracion": 6.83,
      "texto": "Ustedes tienen que ponerme ahora en altavoz, que va a pisar a la capilla el mensaje de texto, que ya le llevo el código.",
      "confianza": 0.688,
      "texto_original": "Ustedes tienen que ponerme ahora en altavoz, que va a pisar a la capilla el mensaje de texto, que ya le llevo el código.",
      "rol": "AGENTE"
    },
    {
      "hablante": "Hablante A",
      "inicio": 416.44,
      "fin": 419.64,
      "duracion": 3.2,
      "texto": "Le voy a llevar un mensajito desde el remitente 223.",
      "confianza": 0.503,
      "texto_original": "Le voy a llevar un mensajito desde el remitente 223.",
      "rol": "AGENTE"
    },
    {
      "hablante": "Hablante A",
      "inicio": 419.84,
      "fin": 427.31,
      "duracion": 7.47,
      "texto": "Ahí me traje, le va a aparecer el mensaje, va a tener cuatro dígitos y una fecha de vencimiento, yo necesito que me lo editen la llamada.",
      "confianza": 0.656,
      "texto_original": "Ahí me traje, le va a aparecer el mensaje, va a tener cuatro dígitos y una fecha de vencimiento, yo necesito que me lo editen la llamada.",
      "rol": "AGENTE"
    },
    {
      "hablante": "Hablante A",
      "inicio": 427.73,
      "fin": 433.7,
      "duracion": 5.97,
      "texto": "Eso es para que siga conservando el mismo número de líneas.",
      "confianza": 0.661,
      "texto_original": "Eso es para que siga conservando el mismo número de líneas.",
      "rol": "AGENTE"
    },
    {
      "hablante": "Hablante A",
      "inicio": 433.72,
      "fin": 433.78,
      "duracion": 0.06,
      "texto": "Sí.",
      "confianza": 0.059,
      "texto_original": "Sí.",
      "rol": "AGENTE"
    },
    {
      "hablante": "Hablante A",
      "inicio": 433.8,
      "fin": 436.54,
      "duracion": 2.74,
      "texto": "¿Cómo era tu nombre?",
      "confianza": 0.545,
      "texto_original": "¿Cómo era tu nombre?",
      "rol": "AGENTE"
    },
    {
      "hablante": "Hablante A",
      "inicio": 436.56,
      "fin": 436.76,
      "duracion": 0.2,
      "texto": "Abigay.",
      "confianza": 0.159,
      "texto_original": "Abigay.",
      "rol": "AGENTE"
    },
    {
      "hablante": "Hablante A",
      "inicio": 436.78,
      "fin": 437.76,
      "duracion": 0.98,
      "texto": "Abigay, escúchame.",
      "confianza": 0.404,
      "texto_original": "Abigay, escúchame.",
      "rol": "AGENTE"
    },
    {
      "hablante": "Hablante A",
      "inicio": 437.78,
      "fin": 441.14,
      "duracion": 3.36,
      "texto": "Mi padre viene a mi casa así trabajando.",
      "confianza": 0.457,
      "texto_original": "Mi padre viene a mi casa así trabajando.",
      "rol": "AGENTE"
    },
    {
      "hablante": "Hablante A",
      "inicio": 441.56,
      "fin": 444.17,
      "duracion": 2.6,
      "texto": "Y se me complica que tengo que terminar la bucha y voy a trabajar.",
      "confianza": 0.483,
      "texto_original": "Y se me complica que tengo que terminar la bucha y voy a trabajar.",
      "rol": "AGENTE"
    },
    {
      "hablante": "Hablante A",
      "inicio": 444.69,
      "fin": 449.27,
      "duracion": 4.59,
      "texto": "¿Cómo podemos asistir tarde?",
      "confianza": 0.566,
      "texto_original": "¿Cómo podemos asistir tarde?",
      "rol": "AGENTE"
    },
    {
      "hablante": "Hablante A",
      "inicio": 449.29,
      "fin": 451.98,
      "duracion": 2.68,
      "texto": "¿Para mañana puede ser?",
      "confianza": 0.66,
      "texto_original": "¿Para mañana puede ser?",
      "rol": "AGENTE"
    },
    {
      "hablante": "Hablante A",
      "inicio": 452.0,
      "fin": 459.99,
      "duracion": 7.99,
      "texto": "Mire, me puede pasar este mensajito y yo de última, cuando salgo de trabajar lo vuelvo a llamar para poder hacer el cierre comercial, que es la parte más larga.",
      "confianza": 0.727,
      "texto_original": "Mire, me puede pasar este mensajito y yo de última, cuando salgo de trabajar lo vuelvo a llamar para poder hacer el cierre comercial, que es la parte más larga.",
      "rol": "AGENTE"
    },
    {
      "hablante": "Hablante A",
      "inicio": 460.19,
      "fin": 466.32,
      "duracion": 6.13,
      "texto": "Pero necesitaría que me edite el correo de portabilidad, por favor.",
      "confianza": 0.499,
      "texto_original": "Pero necesitaría que me edite el correo de portabilidad, por favor.",
      "rol": "AGENTE"
    },
    {
      "hablante": "Hablante A",
      "inicio": 466.34,
      "fin": 469.99,
      "duracion": 3.65,
      "texto": "Me lo puede editar ahora en la llamada.",
      "confianza": 0.277,
      "texto_original": "Me lo puede editar ahora en la llamada.",
      "rol": "AGENTE"
    },
    {
      "hablante": "Hablante B",
      "inicio": 471.96,
      "fin": 478.81,
      "duracion": 6.85,
      "texto": "A ver, acuerden meterse las pasillas en el mensaje de texto.",
      "confianza": 0.502,
      "texto_original": "A ver, acuerden meterse las pasillas en el mensaje de texto.",
      "rol": "CLIENTE"
    },
    {
      "hablante": "Hablante B",
      "inicio": 478.83,
      "fin": 481.69,
      "duracion": 2.86,
      "texto": "Debe ser el último que le haya llegado desde el remitente 223.",
      "confianza": 0.694,
      "texto_original": "Debe ser el último que le haya llegado desde el remitente 223.",
      "rol": "CLIENTE"
    },
    {
      "hablante": "Hablante B",
      "inicio": 481.73,
      "fin": 486.04,
      "duracion": 4.31,
      "texto": "¿Es el mensaje de texto?",
      "confianza": 0.553,
      "texto_original": "¿Es el mensaje de texto?",
      "rol": "CLIENTE"
    },
    {
      "hablante": "Hablante B",
      "inicio": 486.06,
      "fin": 495.73,
      "duracion": 9.67,
      "texto": "Sí, SME.",
      "confianza": 0.644,
      "texto_original": "Sí, SME.",
      "rol": "CLIENTE"
    },
    {
      "hablante": "Hablante B",
      "inicio": 495.75,
      "fin": 497.05,
      "duracion": 1.3,
      "texto": "Ahí ya se pudo meter.",
      "confianza": 0.678,
      "texto_original": "Ahí ya se pudo meter.",
      "rol": "CLIENTE"
    },
    {
      "hablante": "Hablante A",
      "inicio": 499.23,
      "fin": 522.25,
      "duracion": 23.02,
      "texto": "¿Ahí lo puedo encontrar, Javier?",
      "confianza": 0.591,
      "texto_original": "¿Ahí lo puedo encontrar, Javier?",
      "rol": "AGENTE"
    },
    {
      "hablante": "Hablante A",
      "inicio": 522.94,
      "fin": 524.68,
      "duracion": 1.74,
      "texto": "¿Dónde es?",
      "confianza": 0.122,
      "texto_original": "¿Dónde es?",
      "rol": "AGENTE"
    },
    {
      "hablante": "Hablante A",
      "inicio": 524.7,
      "fin": 529.21,
      "duracion": 4.51,
      "texto": "Eh, sí.",
      "confianza": 0.252,
      "texto_original": "Eh, sí.",
      "rol": "AGENTE"
    },
    {
      "hablante": "Hablante A",
      "inicio": 529.53,
      "fin": 529.79,
      "duracion": 0.26,
      "texto": "Dígame.",
      "confianza": 0.386,
      "texto_original": "Dígame.",
      "rol": "AGENTE"
    },
    {
      "hablante": "Hablante A",
      "inicio": 529.81,
      "fin": 532.33,
      "duracion": 2.52,
      "texto": "¿24-43 puede ser?",
      "confianza": 0.436,
      "texto_original": "¿24-43 puede ser?",
      "rol": "AGENTE"
    },
    {
      "hablante": "Hablante A",
      "inicio": 532.35,
      "fin": 534.33,
      "duracion": 1.98,
      "texto": "Eh, solamente usted lo puede ver.",
      "confianza": 0.66,
      "texto_original": "Eh, solamente usted lo puede ver.",
      "rol": "AGENTE"
    },
    {
      "hablante": "Hablante A",
      "inicio": 534.35,
      "fin": 535.32,
      "duracion": 0.96,
      "texto": "Yo no lo veo.",
      "confianza": 0.652,
      "texto_original": "Yo no lo veo.",
      "rol": "AGENTE"
    },
    {
      "hablante": "Hablante A",
      "inicio": 535.36,
      "fin": 537.12,
      "duracion": 1.76,
      "texto": "Así que tiene que dictármelo bien.",
      "confianza": 0.67,
      "texto_original": "Así que tiene que dictármelo bien.",
      "rol": "AGENTE"
    },
    {
      "hablante": "Hablante A",
      "inicio": 537.14,
      "fin": 538.08,
      "duracion": 0.94,
      "texto": "Sí, 24-43.",
      "confianza": 0.576,
      "texto_original": "Sí, 24-43.",
      "rol": "AGENTE"
    },
    {
      "hablante": "Hablante A",
      "inicio": 538.1,
      "fin": 538.36,
      "duracion": 0.26,
      "texto": "Bien.",
      "confianza": 0.811,
      "texto_original": "Bien.",
      "rol": "AGENTE"
    },
    {
      "hablante": "Hablante A",
      "inicio": 538.38,
      "fin": 539.52,
      "duracion": 1.14,
      "texto": "¿Y la fecha de vencimiento?",
      "confianza": 0.636,
      "texto_original": "¿Y la fecha de vencimiento?",
      "rol": "AGENTE"
    },
    {
      "hablante": "Hablante A",
      "inicio": 539.54,
      "fin": 542.35,
      "duracion": 2.8,
      "texto": "Eh, 27-01.",
      "confianza": 0.681,
      "texto_original": "Eh, 27-01.",
      "rol": "AGENTE"
    },
    {
      "hablante": "Hablante A",
      "inicio": 543.45,
      "fin": 544.07,
      "duracion": 0.62,
      "texto": "Perfecto.",
      "confianza": 0.584,
      "texto_original": "Perfecto.",
      "rol": "AGENTE"
    },
    {
      "hablante": "Hablante A",
      "inicio": 544.09,
      "fin": 545.63,
      "duracion": 1.54,
      "texto": "¿Le puede sacar una captura de pantalla?",
      "confianza": 0.62,
      "texto_original": "¿Le puede sacar una captura de pantalla?",
      "rol": "AGENTE"
    },
    {
      "hablante": "Hablante A",
      "inicio": 545.65,
      "fin": 547.53,
      "duracion": 1.88,
      "texto": "Me lo mando al WhatsApp y no lo molesto más.",
      "confianza": 0.591,
      "texto_original": "Me lo mando al WhatsApp y no lo molesto más.",
      "rol": "AGENTE"
    },
    {
      "hablante": "Hablante B",
      "inicio": 550.18,
      "fin": 551.68,
      "duracion": 1.5,
      "texto": "Eh, ay, cómo hago hasta ahora.",
      "confianza": 0.197,
      "texto_original": "Eh, ay, cómo hago hasta ahora.",
      "rol": "CLIENTE"
    },
    {
      "hablante": "Hablante B",
      "inicio": 551.89,
      "fin": 561.39,
      "duracion": 9.49,
      "texto": "Tiene que apretar el botón de encendido y apagado junto con el botón de bajar el volumen, los dos al mismo tiempo, y así le saca una captura.",
      "confianza": 0.764,
      "texto_original": "Tiene que apretar el botón de encendido y apagado junto con el botón de bajar el volumen, los dos al mismo tiempo, y así le saca una captura.",
      "rol": "CLIENTE"
    },
    {
      "hablante": "Hablante B",
      "inicio": 561.43,
      "fin": 573.84,
      "duracion": 12.41,
      "texto": "O si no, pope el mensaje y pégelo en el chat de WhatsApp que tiene conmigo.",
      "confianza": 0.724,
      "texto_original": "O si no, pope el mensaje y pégelo en el chat de WhatsApp que tiene conmigo.",
      "rol": "CLIENTE"
    },
    {
      "hablante": "Hablante B",
      "inicio": 573.86,
      "fin": 574.1,
      "duracion": 0.24,
      "texto": "Bueno, dale.",
      "confianza": 0.097,
      "texto_original": "Bueno, dale.",
      "rol": "CLIENTE"
    },
    {
      "hablante": "Hablante B",
      "inicio": 574.12,
      "fin": 579.81,
      "duracion": 5.69,
      "texto": "Yo le acabo de mandar un mensajito, que es la foto de donde está ubicada la sucursala, porque ahí no más le va a salir.",
      "confianza": 0.547,
      "texto_original": "Yo le acabo de mandar un mensajito, que es la foto de donde está ubicada la sucursala, porque ahí no más le va a salir.",
      "rol": "CLIENTE"
    },
    {
      "hablante": "Hablante B",
      "inicio": 580.4,
      "fin": 598.02,
      "duracion": 17.62,
      "texto": "¡Adiós!",
      "confianza": 0.38,
      "texto_original": "¡Adiós!",
      "rol": "CLIENTE"
    }
  ],
  "transcripcion_completa": "Hola, buenas tardes. Hola, es Javier, un gusto. Les estoy hablando desde la área de portabilidad de Modestar. Muy bien, era para comentarles las promociones, se han actualizado y tenemos algo con mayor cantidad de gigas y un poco más económico. Le comento las promociones. Tenemos lo que sería un plan de 14 gigas en $6,450 pesos y otro plan de 18 gigas en $8,000 pesos. El más económico me interesa. El de $6.450? Sí. ¿Precio pico? ¿Cómo? ¿Este monte es pico? Sí, totalmente. Tiene un descuento... Yo me cambié de línea porque la verdad es que la verdad es que me agundaron 10.000 veces a movistar. Por eso me cambié a claro. Claro, sí, sí, sí. La entiendo totalmente. Sí, ese precio pico es un descuento durante $6.000. Yo siempre les digo a mis clientes que en el quinto mes lo pueden, digamos, actualizar al plan para evitar que le venga el valor total del plan antes de que se le venga la promoción. ¿Entiendes? Y bueno, lo actualizo ustedes en la aplicación de Movistar y sigue gozando de los mismos beneficios. ¿Cómo? ¿Te lo conservo? Sí, va a seguir teniendo el mismo número, solamente que se va a cambiar de compañía. Y bueno, le comento que usted también tiene WhatsApp gratis, llamadas libres a cualquier compañía y 20 días de regalo durante 30 días, que usted los activa en el momento en el que lo desea usar. ¿Seguimos entonces con panista la promoción? Sí, pero mira, yo quiero que sea tipo, que normativa que sea poeta. Hace dos meses me meten el abono. Sí, lo entiendo totalmente. Duran seis meses la promoción, se mantiene el precio y después cualquier cosa que usted lo tiene que cambiar a la promoción o supongas que necesita más vidas o algo así lo puede excepcionar en la aplicación. Sí, a mí se me pasó. y buscar alguna cosa y poder hacer otra cosa. Claro, sí sí. Pero bueno, si... Lo hacemos. Bueno, entonces, ¿necesitaría que me pase un correo electrónico que a ese le van a llegar las facturas? Sí. Dígame. No, pero es que... Más que que levantar, yo con eso... Quiero... No, yo no creo que venga nunca. ¿Puede ser mañana? No, no hay problema. Al final, después de última, me lo paso a usted mañana y yo lo adjunto. O si no me fijo, ¿cuál me asegura con el sistema? Le pregunto a ver si usted más o menos se acuerda, si es el de firme. Y si no, cualquier cosita lo asuntamos mañana. No hay ningún tipo de problema. Yo en eso estoy totalmente analógico. No hay problema. Lo entiendo. Bueno, bueno, bien. ¿Tiene únicamente este número de teléfono o algún otro a su nombre? Bueno, a ver, aguardemos un segundito, le hago una consulta. ¿Usted tiene chip físico, lo que es la tarjetita de grabada que se pone en el dispositivo? ¿Usted tiene chip físico, que es la tarjetita de grabada que se pone en el celular? Bien, me podría decir entonces, su provincia de localidad sigue haciendo una supersal para que vaya a retirar su morado chip de Movistar. Yo voy a estar en Pilar, por ahí está bueno el aire. Bien, a ver. A guardar un segundito que ahí le digo cuál me figura. Me figura una por la calle Río Dabia. Hablaste por San. Exactamente, por la calle Río Dabia y otra por la calle Tupumán en Chile. Sí, conozco. Bien, le voy a signar la de la calle Río Dabia que tiene mayor cantidad de horario de atención. Sí. Sí, que vale, dale. Te lo voy a mandar. ¿Te lo mando a la domicilio? ¿Cómo? ¿Te lo mando a la domicilio eso? Eh, no, no, no. Usted tiene que ir a retirar su chip a esa sucursal. Listo, bueno. Vos avisadme cuando tengo que ir a buscarlo y yo voy luego. Sí, ya mañana mismo lo puede ir a buscar. Ahí le acabo de mandarlo horarios de atención por WhatsApp y ¿dónde está ubicada la sucursal? Sí, lo conozco, en la esquina, lo conozco. Bien, perfecto. Eh, a ver. No voy a fijar... No, no me figura ningún correo electrónico en el sistema, así que apenas puede charlar con tu hija, me avisa. Dale, dale, dale, se te avisa. A ver, el tema es que escute conmigo mi nieta, ¿viste? Hoy. Y yo me voy a la casa a trabajar y nunca viene más tarde. Así le pregunto si lo puedo pasar hoy, si no, mañana a mi mamá si lo puedo pasar. Bueno, no es problema. Genial. Si eres hoy, mejor. Bien, entonces... Sí, sí, sí, eso tranquilo. Voy, voy, te mando un roll que te hiciera un misil, eh. No, bueno, un montón, eh. Un poco para tanto. Vale, vale, vale. Bueno, entonces, oye, ahora le voy a empezar a hacer un cierre comercial, ¿sí? Esto es para corroborar de que todos los datos, eh, que ustedes estén bien, que hayan entendido cómo se realiza todo el proceso, si tienen alguna movilidad, primer frena, y lo corroboramos. Pero no, antes le voy a mandar el código de portabilidad. ¿Sabe cómo ver los mensajes del texto, verdad? Sí, sí. Bien, perfecto. Entonces, yo ya, cuando le llegue, le aviso. Ustedes tienen que ponerme ahora en altavoz, que va a pisar a la capilla el mensaje de texto, que ya le llevo el código. Le voy a llevar un mensajito desde el remitente 223. Ahí me traje, le va a aparecer el mensaje, va a tener cuatro dígitos y una fecha de vencimiento, yo necesito que me lo editen la llamada. Eso es para que siga conservando el mismo número de líneas. Sí. ¿Cómo era tu nombre? Abigay. Abigay, escúchame. Mi padre viene a mi casa así trabajando. Y se me complica que tengo que terminar la bucha y voy a trabajar. ¿Cómo podemos asistir tarde? ¿Para mañana puede ser? Mire, me puede pasar este mensajito y yo de última, cuando salgo de trabajar lo vuelvo a llamar para poder hacer el cierre comercial, que es la parte más larga. Pero necesitaría que me edite el correo de portabilidad, por favor. Me lo puede editar ahora en la llamada. A ver, acuerden meterse las pasillas en el mensaje de texto. Debe ser el último que le haya llegado desde el remitente 223. ¿Es el mensaje de texto? Sí, SME. Ahí ya se pudo meter. ¿Ahí lo puedo encontrar, Javier? ¿Dónde es? Eh, sí. Dígame. ¿24-43 puede ser? Eh, solamente usted lo puede ver. Yo no lo veo. Así que tiene que dictármelo bien. Sí, 24-43. Bien. ¿Y la fecha de vencimiento? Eh, 27-01. Perfecto. ¿Le puede sacar una captura de pantalla? Me lo mando al WhatsApp y no lo molesto más. Eh, ay, cómo hago hasta ahora. Tiene que apretar el botón de encendido y apagado junto con el botón de bajar el volumen, los dos al mismo tiempo, y así le saca una captura. O si no, pope el mensaje y pégelo en el chat de WhatsApp que tiene conmigo. Bueno, dale. Yo le acabo de mandar un mensajito, que es la foto de donde está ubicada la sucursala, porque ahí no más le va a salir. ¡Adiós!",
  "calidad": {
    "confianza_promedio": 0.502,
    "metodo_diarizacion": "pausas_fallback",
    "tiempo_procesamiento": 16.8
  },
  "metadata": {
    "modelo": "whisperx_medium",
    "diarizacion": "pausas",
    "dispositivo": "cuda",
    "fecha": "2026-01-26T05:30:12.306143",
    "version": "5.0_ecapa"
  },
  "_correccion_diarizacion": {
    "fecha_correccion": "2026-01-26T06:35:39.364525",
    "agente_identificado": "Hablante A",
    "scores_hablantes": {
      "Hablante A": 0.5,
      "Hablante B": -1.0
    }
  },
  "info_llamada": {
    "id_interaccion": "260119175703281_MIT_01997",
    "fecha_inicio": "19/1/2026 17:57:03",
    "agente": {
      "nombre": "MZA 65",
      "login": "mza65",
      "equipo": "1"
    },
    "tiempos": {
      "duracion_total": 600,
      "talking_time": 585,
      "hold": 0,
      "acw": 15,
      "en_cola": 0
    },
    "resultado": {
      "origen_corte": "Cliente",
      "causa_terminacion": "Se contacta con el operador",
      "tipificacion": "Venta"
    },
    "campana": {
      "empresa": "AZO",
      "campana": "MVS_MZA_OUT",
      "lote": "nan"
    },
    "cliente": {
      "telefono": "90111535691934.0",
      "nombre": "nan"
    },
    "sentido": "Saliente"
  },
  "_procesamiento": {
    "fecha": "2026-01-26T06:35:39.364979",
    "version": "1.0",
    "archivo_original": "amza65_1_260119175703281_MIT_01997_transcripcion.json",
    "id_interaccion": "260119175703281_MIT_01997",
    "tiene_metadatos_llamada": true
  }
}