{
  "archivo": "amza60_1_260123193504370_ACD_05771.wav",
  "duracion_segundos": 79.94,
  "num_segmentos": 4,
  "num_hablantes": 1,
  "hablantes": [
    "Hablante A"
  ],
  "tiempo_por_hablante": {
    "Hablante A": 79.51
  },
  "idioma": "es",
  "conversacion": [
    {
      "hablante": "Hablante A",
      "inicio": 0.03,
      "fin": 18.19,
      "duracion": 18.16,
      "texto": "No, no, no.",
      "confianza": 0.564,
      "texto_original": "No, no, no.",
      "rol": "AGENTE"
    },
    {
      "hablante": "Hablante A",
      "inicio": 18.17,
      "fin": 45.21,
      "duracion": 27.04,
      "texto": "¿Qué pasa?",
      "confianza": 0.466,
      "texto_original": "¿Qué pasa?",
      "rol": "AGENTE"
    },
    {
      "hablante": "Hablante A",
      "inicio": 45.64,
      "fin": 74.98,
      "duracion": 29.33,
      "texto": "A ver, una de ustedes, por lo que le he dicho, es que él es el presidente de la Comunidad Nacional de Ciudadanos, el presidente de la Comunidad Nacional de Ciudadanos, el presidente de la Comunidad Nacional de Ciudadanos, el presidente de la Comunidad Nacional de Ciudadanos, el presidente de la Comunidad Nacional de Ciudadanos, el presidente de la Comunidad Nacional de Ciudadanos, el presidente de la Comunidad Nacional de Ciudadanos, el presidente de la Comunidad Nacional",
      "confianza": 0.197,
      "texto_original": "A ver, una de ustedes, por lo que le he dicho, es que él es el presidente de la Comunidad Nacional de Ciudadanos, el presidente de la Comunidad Nacional de Ciudadanos, el presidente de la Comunidad Nacional de Ciudadanos, el presidente de la Comunidad Nacional de Ciudadanos, el presidente de la Comunidad Nacional de Ciudadanos, el presidente de la Comunidad Nacional de Ciudadanos, el presidente de la Comunidad Nacional de Ciudadanos, el presidente de la Comunidad Nacional",
      "rol": "AGENTE"
    },
    {
      "hablante": "Hablante A",
      "inicio": 74.96,
      "fin": 79.94,
      "duracion": 4.98,
      "texto": "¿Qué es eso?",
      "confianza": 0.591,
      "texto_original": "¿Qué es eso?",
      "rol": "AGENTE"
    }
  ],
  "transcripcion_completa": "No, no, no. ¿Qué pasa? A ver, una de ustedes, por lo que le he dicho, es que él es el presidente de la Comunidad Nacional de Ciudadanos, el presidente de la Comunidad Nacional de Ciudadanos, el presidente de la Comunidad Nacional de Ciudadanos, el presidente de la Comunidad Nacional de Ciudadanos, el presidente de la Comunidad Nacional de Ciudadanos, el presidente de la Comunidad Nacional de Ciudadanos, el presidente de la Comunidad Nacional de Ciudadanos, el presidente de la Comunidad Nacional ¿Qué es eso?",
  "calidad": {
    "confianza_promedio": 0.454,
    "metodo_diarizacion": "pausas_fallback",
    "tiempo_procesamiento": 5.2
  },
  "metadata": {
    "modelo": "whisperx_medium",
    "diarizacion": "pausas",
    "dispositivo": "cuda",
    "fecha": "2026-01-26T05:04:32.984803",
    "version": "5.0_ecapa"
  },
  "_correccion_diarizacion": {
    "fecha_correccion": "2026-01-26T06:35:38.439083",
    "agente_identificado": "Hablante A",
    "scores_hablantes": {
      "Hablante A": 0.0
    }
  },
  "info_llamada": {
    "id_interaccion": "260123193504370_ACD_05771",
    "fecha_inicio": "23/1/2026 19:35:04",
    "agente": {
      "nombre": "MZA 60",
      "login": "mza60",
      "equipo": "0"
    },
    "tiempos": {
      "duracion_total": 140,
      "talking_time": 78,
      "hold": 0,
      "acw": 32,
      "en_cola": 0
    },
    "resultado": {
      "origen_corte": "Cliente",
      "causa_terminacion": "Se contacta con el operador",
      "tipificacion": "Se corta durante la conversacion"
    },
    "campana": {
      "empresa": "AZO",
      "campana": "MVS_MZA",
      "lote": "20260123_MZA_TT_MIXTO"
    },
    "cliente": {
      "telefono": "111563721149.0",
      "nombre": "nan"
    },
    "sentido": "Discador Predictivo"
  },
  "_procesamiento": {
    "fecha": "2026-01-26T06:35:38.439128",
    "version": "1.0",
    "archivo_original": "amza60_1_260123193504370_ACD_05771_transcripcion.json",
    "id_interaccion": "260123193504370_ACD_05771",
    "tiene_metadatos_llamada": true
  }
}